setup.py
nose_capturestderr/__init__.py
nose_capturestderr.egg-info/PKG-INFO
nose_capturestderr.egg-info/SOURCES.txt
nose_capturestderr.egg-info/dependency_links.txt
nose_capturestderr.egg-info/entry_points.txt
nose_capturestderr.egg-info/requires.txt
nose_capturestderr.egg-info/top_level.txt