Metadata-Version: 1.0
Name: nose-capturestderr
Version: 1.0
Summary: HTML report generation plugin for nose
Home-page: http://github.com/sio2project/nose-capturestderr
Author: The SIO2 Project Team
Author-email: sio2@sio2project.mimuw.edu.pl
License: GPL
Platform: UNKNOWN
